adder_r1t/rca.sv
`timescale 1ns / 1ps
//======================
// Module Name: N-bit Ripple-Carry Adder (RCA)
// File: rca.v
// Engineer: Daniel Grib
// Create Date: 10/23/25
//
// Description: This is my implementation for the ripple-carry adder.
//              It is based on the traditional interpretation of this
//              type of adder. It combines Full Adders in a chain
//              using a structural behavior.
//======================
module rca #(parameter int N = 8)(
    input  logic [N-1:0] A, B,
    input  logic       Cin,
    output logic [N-1:0] Sum,
    output logic       Cout);

    // Wires between Full Adders
    logic [N:0] carry;
    assign carry[0] = Cin;

    // Instantiate Full Adder Loop using genvar
    genvar i;
    generate
        for (i = 0; i < N; i++) begin : adderStage
            fullAdder fA (
                .a(A[i]), .b(B[i]),
                .cin(carry[i]), .sum(Sum[i]),
                .cout(carry[i+1])
            );
        end
    endgenerate

    assign Cout = carry[N];

endmodule


module fullAdder (
    input  logic a, b, cin,
    output logic sum, cout);

    wire w1, w2, w3;

    xor g1 (w1, a, b);
    and g2 (w2, a, b);

    xor g3 (sum, w1, cin);
    and g4 (w3, w1, cin);

    or g5 (cout, w3, w2);
    
endmodule

synth/tb_rca.sv
`timescale 1ns / 1ps

module tb_rca;

    parameter N = 8;   // Change this to test different widths

    // DUT Inputs
    reg  [N-1:0] A, B;
    reg          Cin;

    // DUT Outputs
    wire [N-1:0] Sum;
    wire         Cout;

    // Reference (golden model)
    reg  [N:0] expected;

    // Instantiate DUT
    rca #(N) DUT (
        .A(A), .B(B),
        .Cin(Cin),
        .Sum(Sum),
        .Cout(Cout)
    );

    integer i;

    initial begin
        $display("====== Testing %0d-bit RCA ======", N);

        // --- Directed Test Cases ---
        A = 0; B = 0; Cin = 0; #5;
        expected = A + B + Cin;
        check_output;

        A = 5; B = 10; Cin = 0; #5;
        expected = A + B + Cin;
        check_output;

        A = 8'hFF; B = 1; Cin = 0; #5;   // overflow
        expected = A + B + Cin;
        check_output;

        A = 8'hAA; B = 8'h55; Cin = 1; #5;
        expected = A + B + Cin;
        check_output;

        // --- Random Testing ---
        for (i = 0; i < 50; i = i + 1) begin
            A   = $urandom;
            B   = $urandom;
            Cin = $urandom & 1;
            #5;
            expected = A + B + Cin;
            check_output;
        end

        $display("ALL TESTS PASSED!");
        $finish;
    end

    task check_output;
        if ({Cout, Sum} !== expected) begin
            $display("ERROR: A=%0d B=%0d Cin=%0d | Got %b%b Expected %b",
                     A, B, Cin, Cout, Sum, expected);
            $stop;
        end
    endtask

endmodule

rca.vcd
$date
	Mon Oct 27 18:52:25 2025
$end
$version
	Icarus Verilog
$end
$timescale
	1ps
$end
$scope module tb_rca $end
$var wire 8 ! Sum [7:0] $end
$var wire 1 " Cout $end
$var reg 8 # A [7:0] $end
$var reg 8 $ B [7:0] $end
$var reg 1 % Cin $end
$var reg 9 & expected [8:0] $end
$var integer 32 ' i [31:0] $end
$scope module DUT $end
$var wire 8 ( A [7:0] $end
$var wire 8 ) B [7:0] $end
$var wire 1 % Cin $end
$var wire 9 * carry [8:0] $end
$var wire 8 + Sum [7:0] $end
$var wire 1 " Cout $end
$scope begin adderStage[0] $end
$scope module fA $end
$var wire 1 , a $end
$var wire 1 - b $end
$var wire 1 . cin $end
$var wire 1 / cout $end
$var wire 1 0 sum $end
$var wire 1 1 w1 $end
$var wire 1 2 w2 $end
$var wire 1 3 w3 $end
$upscope $end
$upscope $end
$scope begin adderStage[1] $end
$scope module fA $end
$var wire 1 4 a $end
$var wire 1 5 b $end
$var wire 1 6 cin $end
$var wire 1 7 cout $end
$var wire 1 8 sum $end
$var wire 1 9 w1 $end
$var wire 1 : w2 $end
$var wire 1 ; w3 $end
$upscope $end
$upscope $end
$scope begin adderStage[2] $end
$scope module fA $end
$var wire 1 < a $end
$var wire 1 = b $end
$var wire 1 > cin $end
$var wire 1 ? cout $end
$var wire 1 @ sum $end
$var wire 1 A w1 $end
$var wire 1 B w2 $end
$var wire 1 C w3 $end
$upscope $end
$upscope $end
$scope begin adderStage[3] $end
$scope module fA $end
$var wire 1 D a $end
$var wire 1 E b $end
$var wire 1 F cin $end
$var wire 1 G cout $end
$var wire 1 H sum $end
$var wire 1 I w1 $end
$var wire 1 J w2 $end
$var wire 1 K w3 $end
$upscope $end
$upscope $end
$scope begin adderStage[4] $end
$scope module fA $end
$var wire 1 L a $end
$var wire 1 M b $end
$var wire 1 N cin $end
$var wire 1 O cout $end
$var wire 1 P sum $end
$var wire 1 Q w1 $end
$var wire 1 R w2 $end
$var wire 1 S w3 $end
$upscope $end
$upscope $end
$scope begin adderStage[5] $end
$scope module fA $end
$var wire 1 T a $end
$var wire 1 U b $end
$var wire 1 V cin $end
$var wire 1 W cout $end
$var wire 1 X sum $end
$var wire 1 Y w1 $end
$var wire 1 Z w2 $end
$var wire 1 [ w3 $end
$upscope $end
$upscope $end
$scope begin adderStage[6] $end
$scope module fA $end
$var wire 1 \ a $end
$var wire 1 ] b $end
$var wire 1 ^ cin $end
$var wire 1 _ cout $end
$var wire 1 ` sum $end
$var wire 1 a w1 $end
$var wire 1 b w2 $end
$var wire 1 c w3 $end
$upscope $end
$upscope $end
$scope begin adderStage[7] $end
$scope module fA $end
$var wire 1 d a $end
$var wire 1 e b $end
$var wire 1 f cin $end
$var wire 1 g cout $end
$var wire 1 h sum $end
$var wire 1 i w1 $end
$var wire 1 j w2 $end
$var wire 1 k w3 $end
$upscope $end
$upscope $end
$upscope $end
$scope task check_output $end
$upscope $end
$upscope $end
$enddefinitions $end
#0
$dumpvars
0k
0j
0i
0h
0g
0f
0e
0d
0c
0b
0a
0`
0_
0^
0]
0\
0[
0Z
0Y
0X
0W
0V
0U
0T
0S
0R
0Q
0P
0O
0N
0M
0L
0K
0J
0I
0H
0G
0F
0E
0D
0C
0B
0A
0@
0?
0>
0=
0<
0;
0:
09
08
07
06
05
04
03
02
01
00
0/
0.
0-
0,
b0 +
b0 *
b0 )
b0 (
bx '
bx &
0%
b0 $
b0 #
0"
b0 !
$end
#5000
18
1H
10
b1111 !
b1111 +
1@
19
1I
11
1A
15
1E
1,
1<
b1010 $
b1010 )
b101 #
b101 (
b0 &
#10000
1"
1g
1k
1f
1_
1c
1^
1W
1[
1V
1O
1S
1N
1G
0H
1K
1F
1?
0@
1C
1>
17
08
1;
16
00
b111111110 *
1/
0P
0X
0`
b0 !
b0 +
0h
01
12
1Q
1Y
1a
1i
1-
05
0E
14
1D
1L
1T
1\
1d
b1 $
b1 )
b11111111 #
b11111111 (
b1111 &
#15000
13
11
02
1.
1=
1M
1]
0,
0<
0L
0\
b111111111 *
1%
b1010101 $
b1010101 )
b10101010 #
b10101010 (
b100000000 &
#20000
0^
0"
0F
0W
0g
0?
1X
0[
1h
0k
1@
0C
0V
0f
0>
0N
0O
0_
07
b11 *
0G
0P
0S
0`
0c
18
0;
b10100110 !
b10100110 +
0H
0K
0Q
0a
09
0I
0=
0M
0]
1e
04
1<
0D
0d
b10000001 $
b10000001 )
b100100 #
b100100 (
b0 '
#25000
1P
1N
1G
1K
1F
1?
0@
1C
1>
b11111 *
17
0H
0h
10
03
08
1;
b1110001 !
b1110001 +
1`
1I
0i
01
12
19
1a
1=
1E
0e
1,
14
0<
1\
b1101 $
b1101 )
b1100011 #
b1100011 (
b1 '
b10100110 &
#30000
0h
0f
1F
0_
1?
1`
0c
0@
1C
0^
1>
0W
17
1X
0[
08
1;
0N
0V
16
0G
0O
00
13
b1111 *
1/
1H
0K
b1111000 !
b1111000 +
1P
0S
11
02
0I
1Q
0-
15
0=
0E
1M
04
1<
b10010 $
b10010 )
b1100101 #
b1100101 (
b10 '
b1110001 &
#35000
1h
1f
1_
0`
1c
1^
1W
0X
1[
1V
1O
0P
1S
1N
b11111111 *
1G
1@
0C
b10000100 !
b10000100 +
0H
1K
0A
1B
1I
1=
1U
1]
1D
0T
0\
b1110110 $
b1110110 )
b1101 #
b1101 (
b11 '
b1111000 &
#40000
0h
0f
0_
1`
0c
0^
0W
0@
1X
0[
0>
0V
07
0O
1"
18
0;
1H
0K
b1111010 !
b1111010 +
1P
0S
b100011011 *
1g
09
0I
1J
0Q
1j
05
1E
0M
0U
0]
1e
1T
1\
1d
b10001100 $
b10001100 )
b11101101 #
b11101101 (
b100 '
b10000100 &
#45000
0@
1h
0>
0P
06
1f
07
0N
0/
0`
1_
18
0;
0G
0X
b10001011 !
b10001011 +
10
03
0a
1b
19
0J
0Y
0.
1-
0E
1]
0,
14
0D
0T
b110001000 *
0%
b11000101 $
b11000101 )
b11000110 #
b11000110 (
b101 '
b101111010 &
#50000
1@
1>
17
08
1;
1`
1"
16
1^
1P
0h
1k
1g
b1011100 !
b1011100 +
00
1/
b111001110 *
1W
1Q
1i
0j
01
12
1Z
15
1M
1U
0e
1,
04
1T
b1110111 $
b1110111 )
b11100101 #
b11100101 (
b110 '
b110001011 &
#55000
1[
1V
1O
0P
1S
1N
06
1F
1G
1^
1f
10
0/
0@
1C
1?
1h
0k
08
0;
0H
1K
0X
1W
b10000001 !
b10000001 +
0`
1c
b111111100 *
1_
11
02
1A
0B
0i
1j
09
1:
1I
1Y
0Z
1a
0b
0-
0=
1e
14
1D
0T
0\
b11110010 $
b11110010 )
b10001111 #
b10001111 (
b111 '
b101011100 &
#60000
0N
0G
0^
1H
0K
0W
0F
1X
0[
0?
0V
1@
0C
0O
0>
0P
0S
b110000000 *
07
b10101101 !
b10101101 +
0`
0c
0Q
0:
0a
1b
1-
05
1=
0M
0U
0,
04
0<
1T
1\
b11000101 $
b11000101 )
b11101000 #
b11101000 (
b1000 '
b110000001 &
#65000
1V
1O
1S
1`
18
1N
1^
0"
16
1F
0f
1H
1G
1X
1W
1h
0k
0g
1/
0@
1?
b11101011 !
b11101011 +
0P
0_
0I
1J
0Y
1Z
1i
0j
01
12
0A
1B
1Q
0b
1.
1E
1U
0]
0e
1,
1<
1L
0\
b1111011 *
1%
b101101 $
b101101 )
b10111101 #
b10111101 (
b1001 '
b110101101 &
#70000
08
1@
0V
0f
06
0^
1>
0F
0N
0O
0_
0/
1X
0[
0W
17
0?
1H
0K
0G
0P
0S
1`
0c
b1101101 !
b1101101 +
0h
11
02
1Y
0Z
1:
0B
1I
0J
0Q
1a
0i
0.
0-
15
0=
0U
14
0<
0D
0L
1\
0d
b100 *
0%
b1010 $
b1010 )
b1100011 #
b1100011 (
b1010 '
b11101011 &
#75000
0@
1^
0>
0X
1W
1h
18
07
b11001011 !
b11001011 +
1`
0Y
1Z
1i
01
19
0:
0a
1.
1U
1e
0,
04
0\
b1000001 *
1%
b10101010 $
b10101010 )
b100000 #
b100000 (
b1011 '
b1101101 &
#80000
1F
1?
16
1C
1X
0`
1/
1>
1V
0^
00
13
1H
18
17
b10101010 !
b10101010 +
0@
1O
b101111 *
0W
11
0I
09
1:
1A
1R
0Z
1-
0E
1M
0U
0e
14
1<
1L
0T
1d
b10011 $
b10011 )
b10010110 #
b10010110 (
b1100 '
b11001011 &
#85000
0S
0`
0N
0^
0F
0G
0V
0W
0?
1f
1H
0K
1P
0O
1X
0[
10
03
1@
0C
b10000111 *
1_
b10111111 !
b10111111 +
1h
1I
1Q
0R
1Y
01
12
0A
1b
0i
1E
0M
1U
1]
1,
0<
1\
0d
b1101011 $
b1101011 )
b1010011 #
b1010011 (
b1101 '
b10101010 &
#90000
1N
1G
0H
1K
1F
0"
08
1?
0g
06
0f
0@
1C
1h
0k
0/
b10110001 !
b10110001 +
1P
b11101 *
0_
1A
1i
02
0Q
0b
0-
1=
0]
1e
0,
0L
0\
b10101110 $
b10101110 )
b10 #
b10 (
b1110 '
b10111111 &
#95000
18
16
1/
1`
b11110010 !
b11110010 +
00
12
1a
0.
1-
0=
0E
0e
1,
1<
1D
1\
1d
b11110 *
0%
b100011 $
b100011 )
b11001111 #
b11001111 (
b1111 '
b10110001 &
#100000
1"
1g
0h
1k
1f
1_
0`
1c
1^
0F
1W
0?
0X
1[
1@
0C
1V
0>
1O
06
18
0;
07
0H
0K
b110 !
b110 +
0P
1S
b111110000 *
0/
19
0:
0I
1J
1Q
02
0-
05
1=
1E
1M
0,
0<
b111100 $
b111100 )
b11001010 #
b11001010 (
b10000 '
b11110010 &
#105000
0"
0g
1h
0k
0f
0_
1`
0c
0V
0^
0N
0O
0W
10
0@
1H
b0 *
0G
0P
0S
b11001011 !
b11001011 +
0X
0[
11
0A
1I
0J
0Q
0Y
1-
0=
0E
0M
0U
1]
0\
b1000001 $
b1000001 )
b10001010 #
b10001010 (
b10001 '
b100000110 &
#110000
1"
1g
0h
1k
1f
1_
0`
1c
1^
1W
1[
1V
1O
1S
16
1N
1/
0H
1G
18
0P
0X
b10 !
b10 +
00
13
0I
1J
09
1Q
1Y
1.
1E
0]
1e
04
1L
1T
1\
0d
b111110011 *
1%
b10001001 $
b10001001 )
b1111000 #
b1111000 (
b10010 '
b11001011 &
#115000
0f
0_
1`
0c
0^
0W
1X
0[
0V
0O
08
1@
1H
1P
0S
06
1>
1F
0N
0/
17
1?
0G
b1111100 !
b1111100 +
0h
0k
03
01
1:
1B
0J
0i
1j
0.
0-
15
1=
0E
1]
14
1<
0D
0\
1d
b100001100 *
0%
b11000110 $
b11000110 )
b10110110 #
b10110110 (
b10011 '
b100000010 &
#120000
1V
1O
0H
0P
1S
0F
1^
0"
0>
1N
1@
0C
0?
1X
1W
1`
1h
0g
18
07
1G
b11100111 !
b11100111 +
10
1A
0B
0Y
1Z
0a
1i
0j
19
0:
1J
1.
0=
1E
1U
0]
0e
04
1D
b1110001 *
1%
b101010 $
b101010 )
b10111100 #
b10111100 (
b10100 '
b101111100 &
#125000
0"
0V
0g
0O
1h
0k
1P
0S
0f
0^
16
0N
0_
18
1X
0[
0W
1/
b11 *
0G
b11110111 !
b11110111 +
1`
0c
09
1Y
0Z
12
0J
1a
1-
05
1=
0E
0U
1e
1,
0<
0D
1\
0d
b10000101 $
b10000101 )
b1110001 #
b1110001 (
b10101 '
b11100111 &
#130000
08
06
1V
1^
1>
1N
0/
1@
1P
1O
1X
1W
0h
17
1G
b1110101 !
b1110101 +
1`
11
02
0A
0Q
1R
0Y
1Z
0i
1:
1J
0a
0.
0-
15
0=
1E
1M
1U
0e
14
1D
0\
b1110100 *
0%
b111010 $
b111010 )
b111011 #
b111011 (
b10110 '
b11110111 &
#135000
1"
1g
1k
0H
18
1f
0F
0P
16
1_
0>
0?
0N
1^
1/
0`
1c
0h
07
1@
0C
0G
b111 !
b111 +
0X
1[
1W
01
12
1a
1i
0:
1A
0J
1Y
0Z
1.
1-
05
0E
1]
1e
04
1<
0D
0T
b111100011 *
1%
b11110001 $
b11110001 )
b10101 #
b10101 (
b10111 '
b1110101 &
#140000
0P
0N
0G
0K
0F
0?
0^
1@
0C
0W
0"
0>
1X
0[
0g
06
07
0V
1H
1h
0k
0/
18
0;
b10000001 *
0O
b10101111 !
b10101111 +
0`
0c
1I
0i
02
19
0R
0a
1b
0-
1=
1E
0M
0U
0e
0,
14
0<
0L
1T
1\
b1001100 $
b1001100 )
b1100010 #
b1100010 (
b11000 '
b100000111 &
#145000
1F
1c
1?
1^
0@
1C
1W
1>
0X
1[
17
1V
08
1;
1O
16
1S
1h
1/
1N
1f
1"
0P
00
13
1H
1G
b10001000 !
b10001000 +
0`
1_
b111111111 *
1g
1Q
11
0I
1J
1a
0b
1j
0=
1M
1U
1e
1,
1<
1D
0T
0\
1d
b11111000 $
b11111000 )
b10001111 #
b10001111 (
b11001 '
b10101111 &
#150000
0f
0_
1`
0c
0^
0W
0"
1@
0C
1X
0[
1h
0k
b111111 *
0g
b11111100 !
b11111100 +
1P
0S
0A
1B
0Y
1i
0j
0Q
1R
1=
0U
0e
1L
b1011100 $
b1011100 )
b10011111 #
b10011111 (
b11010 '
b110001000 &
#155000
0@
0>
0H
0X
07
0F
0V
b11010010 !
b11010010 +
18
0;
0?
0O
03
01
12
09
0B
0R
0.
1-
0=
0M
04
0<
0L
b10010 *
0%
b1001001 $
b1001001 )
b10001001 #
b10001001 (
b11011 '
b11111100 &
#160000
1H
1F
1?
1"
1C
1g
1>
0P
1X
0h
1k
17
0N
1V
1f
08
1;
0@
0G
1O
b101000 !
b101000 +
0`
b110101110 *
1_
19
1A
0J
1R
0a
1b
0E
1M
14
1<
0D
1L
1\
b1010001 $
b1010001 )
b11010111 #
b11010111 (
b11100 '
b11010010 &
#165000
0F
0?
1@
0C
0>
0"
07
0P
0g
18
0;
0N
0X
1h
0k
06
0G
0V
0f
0/
1H
0K
0O
b11001110 !
b11001110 +
1`
b0 *
0_
02
1I
0R
1a
0b
0-
15
0M
1e
0,
04
1D
0L
0\
0d
b11000010 $
b11000010 )
b1100 #
b1100 (
b11101 '
b100101000 &
#170000
1P
1N
1>
1f
1G
17
1_
0H
1K
08
1;
1X
0`
1c
1F
16
1V
1^
1@
1?
b10110100 !
b10110100 +
1h
1/
1O
b11111110 *
1W
0A
1B
0i
12
1R
1Z
1-
05
1=
1E
1M
1U
0]
0e
1,
14
0D
1L
1T
1\
b111101 $
b111101 )
b1110111 #
b1110111 (
b11110 '
b11001110 &
#175000
1X
1V
0P
1S
1O
1`
0c
b11101100 !
b11101100 +
1H
0K
13
1Q
0R
0a
1b
11
02
0I
1J
1.
0M
1]
0,
1D
b11111111 *
1%
b1101101 $
b1101101 )
b1111110 #
b1111110 (
b11111 '
b10110100 &
#180000
0"
1F
1N
0g
0^
0f
18
0;
0@
1C
1?
0H
1K
1G
1P
0S
1h
0k
10
03
0W
b11110011 !
b11110011 +
1`
0c
b111111 *
0_
09
1:
1A
0B
1I
0J
0Q
1R
1i
01
12
0Z
1a
0b
15
0=
0E
1M
0U
1e
1,
0T
0\
b11010011 $
b11010011 )
b11111 #
b11111 (
b100000 '
b11101100 &
#185000
0F
1^
16
1>
0?
1W
1f
0H
0K
1h
00
13
1/
08
1;
17
1@
0C
0X
1[
b11010100 !
b11010100 +
1`
b11110111 *
1_
0I
1J
0i
11
02
19
0:
0A
1Y
0a
1b
1E
0e
0,
04
0<
1T
1\
b1011011 $
b1011011 )
b1111000 #
b1111000 (
b100001 '
b11110011 &
#190000
1H
1F
0h
06
1V
1?
0f
0/
0P
1S
1O
1X
0[
08
0;
0@
1C
0_
b1101001 !
b1101001 +
10
03
1Q
0R
0Y
1Z
09
1:
1A
0b
0.
0-
0M
1U
0]
1,
14
1<
0\
b1111100 *
0%
b101010 $
b101010 )
b111111 #
b111111 (
b100010 '
b11010100 &
#195000
0X
0V
0`
1N
0O
0^
1"
1@
0C
00
0H
1K
1G
b10100 !
b10100 +
1P
0S
0W
b100011100 *
1g
0A
1B
01
1I
0J
0Q
0Z
1j
1=
0U
1e
0,
0D
0L
0T
1d
b10001110 $
b10001110 )
b10000110 #
b10000110 (
b100011 '
b1101001 &
#200000
1k
1N
1f
1G
1X
1_
0H
1K
1V
1c
1"
1F
1O
1^
0h
1g
0@
1C
1?
0P
1S
1W
0`
b100001 !
b100001 +
10
1i
0j
1A
0B
1Q
1Z
1a
1.
0E
1U
0e
0<
1D
1L
1T
1\
b111111101 *
1%
b100110 $
b100110 )
b11111010 #
b11111010 (
b100100 '
b100010100 &
#205000
0"
0g
0X
1h
0k
18
0V
0f
16
0O
0_
b1011111 *
1/
1P
0S
b11010011 !
b11010011 +
1`
0c
12
0Q
0a
1-
1E
1,
0D
0L
0\
b101111 $
b101111 )
b10100011 #
b10100011 (
b100101 '
b100100001 &
#210000
1X
1V
0`
16
1>
1O
0^
1f
00
13
1/
08
1;
17
1@
0C
0P
1S
0W
b10111111 *
1_
b10100100 !
b10100100 +
1h
11
02
19
0:
0A
1B
1Q
0Z
1b
0i
0-
05
0E
0U
1]
1<
1D
1L
0T
1\
0d
b1000100 $
b1000100 )
b1011111 #
b1011111 (
b100110 '
b11010011 &
#215000
1N
0`
1G
0^
0H
1K
0V
06
0W
1F
0O
1"
0/
08
0;
1X
0[
0@
1C
1?
1P
0S
1g
b10110001 !
b10110001 +
10
03
09
1:
1Y
1A
0B
0Q
1j
0.
15
1U
1e
0<
0L
1d
b110011100 *
0%
b11100110 $
b11100110 )
b11001011 #
b11001011 (
b100111 '
b10100100 &
#220000
0F
0?
18
1@
0C
1c
16
0>
1^
1f
1"
00
1/
0H
0K
07
0X
1W
0`
1_
b10110 !
b10110 +
0h
1k
b111010010 *
1g
01
12
0I
1J
0:
0Y
1Z
1a
0b
1i
0j
1-
05
1E
04
1T
0\
0d
b11101101 $
b11101101 )
b101001 #
b101001 (
b101000 '
b110110001 &
#225000
0X
0V
1H
0O
1F
0N
1P
0S
0@
1?
0G
b11011 !
b11011 +
10
1Q
0A
1B
0J
1.
0E
1M
0]
1<
0D
1\
b111001011 *
1%
b10110101 $
b10110101 )
b1100101 #
b1100101 (
b101001 '
b100010110 &
#230000
0[
0V
0O
1P
0S
08
0"
0N
06
0^
0g
0F
0G
0/
1X
0W
0`
0c
1h
0k
1@
0?
b10111101 !
b10111101 +
1H
0K
11
02
1Y
0Z
0a
1b
0i
1A
0B
1I
0.
0-
0M
0U
1]
0e
0<
1D
1L
b10000000 *
0%
b1000100 $
b1000100 )
b1111001 #
b1111001 (
b101010 '
b100011011 &
#235000
1`
0"
1N
1^
0g
1>
0f
1@
0H
1G
0X
1W
1h
0k
17
b11010101 !
b11010101 +
1P
b1010100 *
0_
0A
0I
1J
0Y
1Z
1i
1:
0Q
0b
1-
15
0=
1E
1U
0]
1e
0,
14
0L
0\
b10101011 $
b10101011 )
b101010 #
b101010 (
b101011 '
b10111101 &
#240000
0H
0F
1X
0f
0>
0?
1V
0^
0_
1"
18
07
1@
0C
1O
0W
1`
0c
b1110111 !
b1110111 +
0h
1g
01
19
0:
1A
1R
0Z
1a
0i
1j
1.
0-
1M
0U
04
1<
1L
0T
1\
1d
b100110001 *
1%
b10011010 $
b10011010 )
b11011100 #
b11011100 (
b101100 '
b11010101 &
#245000
1H
1F
1?
1k
0@
1C
0X
1f
1"
1>
0N
0V
0`
1_
0h
1g
08
17
0G
b11001 !
b11001 +
1P
0S
0O
0a
1b
1i
0j
11
09
1:
0J
1Q
0R
0.
1=
0E
1]
0e
1,
14
0<
0D
0L
b110001100 *
0%
b1010110 $
b1010110 )
b11000011 #
b11000011 (
b101101 '
b101110111 &
#250000
1N
0"
1G
0f
0g
0H
1K
1P
1`
b11100 *
0_
1X
b1110001 !
b1110001 +
0h
0k
1I
0Q
1a
0b
1Y
0i
0=
1E
0M
0]
1<
1T
0d
b1010 $
b1010 )
b1100111 #
b1100111 (
b101110 '
b100011001 &
#255000
1h
1f
1_
0`
1c
0F
1^
0>
0?
1V
1X
1W
07
0@
0C
b10110001 !
b10110001 +
0H
0K
b11110000 *
1O
0Y
1Z
0:
0A
0I
1J
1R
1-
05
1M
1U
1]
0,
04
0<
1D
1L
0\
b1111001 $
b1111001 )
b111000 #
b111000 (
b101111 '
b1110001 &
#260000
0h
0f
0P
0_
0N
0^
1"
18
0`
0c
b100111 !
b100111 +
1@
0G
0W
b100100000 *
1g
19
0a
1A
0J
0Z
1j
15
0E
0U
0]
1e
1<
0D
0T
1d
b10010011 $
b10010011 )
b10010100 #
b10010100 (
b110000 '
b10110001 &
#265000
1>
17
08
1;
1P
1k
16
1N
1f
1"
1/
1@
1G
1_
b110101 !
b110101 +
0h
1g
01
12
0A
1J
1b
1i
0j
1.
1E
1]
1,
0<
1D
1\
0d
b110110111 *
1%
b11011011 $
b11011011 )
b1011001 #
b1011001 (
b110001 '
b100100111 &
#270000
b110010 '
b100110101 &
