adder_r1t/rca.sv
`timescale 1ns / 1ps
//======================
// Module Name: N-bit Ripple-Carry Adder (RCA)
// File: rca.v
// Engineer: Daniel Grib
// Create Date: 10/23/25
//
// Description: This is my implementation for the ripple-carry adder.
//              It is based on the traditional interpretation of this
//              type of adder. It combines Full Adders in a chain
//              using a structural behavior.
//======================
module rca (
    parameter N,
    input  logic [N-1:0] A, B,
    input  logic       Cin,
    output logic [N-1:0] Sum,
    output logic       Cout);

    // Wires between Full Adders
    logic [N:0] carry;
    assign carry[0] = Cin;

    // Instantiate Full Adder Loop using genvar
    genvar i;
    generate
        for (i = 0; i < N; i++) begin : adderStage
            fullAdder fA (
                .a(A[i]), .b(B[i]),
                .cin(carry[i]), .sum(Sum[i]),
                .cout(carry[i+1])
            );
        end
    endgenerate

    assign Cout = carry[N];

endmodule


module fullAdder (
    input  logic a, b, cin,
    output logic sum, cout);

    wire w1, w2, w3;

    xor g1 (w1, a, b);
    and g2 (w2, a, b);

    xor g3 (sum, w1, cin);
    and g4 (w3, w1, cin);

    or g5 (cout, w3, w2);
    
endmodule

tb/tb_rca.sv
`timescale 1ns / 1ps

module tb_rca;

    // WIDTH LIST
    localparam int NUM_CONFIGS = 4;
    localparam int WIDTH_0 = 8;
    localparam int WIDTH_1 = 16;
    localparam int WIDTH_2 = 32;
    localparam int WIDTH_3 = 64;

    


    // Loop through each width
    genvar i;
    generate
        for (i = 0; i < NUM_CONFIGS; i++) begin : WIDTH_TEST
            localparam int N =
                (i == 0) ? WIDTH_0 :
                (i == 1) ? WIDTH_1 :
                (i == 2) ? WIDTH_2 : WIDTH_3;

            // DUT Inputs
            logic  [N-1:0] A, B;
            logic          Cin;

            // DUT Outputs
            logic [N-1:0] Sum;
            logic         Cout;

            // Expected
            logic  [N:0]   expected;
            logic  [N-1:0] expected_sum;
            logic          expected_cout;

            // Instantiate DUT
            rca #(.N(N)) DUT (
                .A(A), .B(B),
                .Cin(Cin),
                .Sum(Sum),
                .Cout(Cout)
            );

            initial begin : SIM
                int j;
                $display("=== Testing %d-bit RCA ===", N);

                //Waveform dump
                #(1000*i); // delay start time for each config
                $dumpfile($sformatf("rca_%0dbit.vcd", N));
                $dumpvars(0, tb_rca);

                // --- Directed tests ---
                A = '0; B = '0; Cin = 0; #5;
                expected = A + B + Cin; check_output();

                A = 5; B = 10; Cin = 0; #5;
                expected = A + B + Cin; check_output();

                A = '1; B = 1; Cin = 0; #5;  // overflow
                expected = A + B + Cin; check_output();

                // --- Random tests ---
                for (j = 0; j < 20; j++) begin
                    A   = $urandom;
                    B   = $urandom;
                    Cin = $urandom & 1;
                    #5;
                    expected = A + B + Cin;
                    expected_sum = expected[N-1:0];
                    expected_cout = expected[N];
                    check_output();
                end

                $display("%d-bit RCA PASSED ALL TESTS\n", N);
            end : SIM

            // Self-checking task (lexically scoped)
            task check_output;
                if ({Cout, Sum} !== expected) begin
                    $display("ERROR (%d-bit): A=%h B=%h Cin=%b -> Got %b%b Expected %b",
                             N, A, B, Cin, Cout, Sum, expected);
                    $stop;
                end
            endtask

        end : WIDTH_TEST
    endgenerate

    // Stop the entire simulation when all instances finish
    initial begin
        #10000;
        $display("=== ALL WIDTH TESTS COMPLETED ===");
        $finish;
    end

endmodule

rca_8bit.vcd
$date
	Mon Oct 27 19:13:04 2025
$end
$version
	Icarus Verilog
$end
$timescale
	1ps
$end
$scope module tb_rca $end
$scope begin WIDTH_TEST[0] $end
$var wire 8 ! Sum [7:0] $end
$var wire 1 " Cout $end
$var reg 8 # A [7:0] $end
$var reg 8 $ B [7:0] $end
$var reg 1 % Cin $end
$var reg 9 & expected [8:0] $end
$var reg 1 ' expected_cout $end
$var reg 8 ( expected_sum [7:0] $end
$upscope $end
$upscope $end
$enddefinitions $end
#0
$dumpvars
bx (
x'
bx &
0%
b0 $
b0 #
0"
b0 !
$end
#5000
b1111 !
b1010 $
b101 #
b0 &
#10000
1"
b0 !
b1 $
b11111111 #
b1111 &
#15000
0"
b10100110 !
1%
b10000001 $
b100100 #
b100000000 &
#20000
b1110001 !
b1101 $
b1100011 #
0'
b10100110 (
b10100110 &
#25000
b1111000 !
b10010 $
b1100101 #
b1110001 (
b1110001 &
#30000
b10000100 !
b1110110 $
b1101 #
b1111000 (
b1111000 &
#35000
1"
b1111010 !
b10001100 $
b11101101 #
b10000100 (
b10000100 &
#40000
b10001011 !
0%
b11000101 $
b11000110 #
1'
b1111010 (
b101111010 &
#45000
1"
b1011100 !
b1110111 $
b11100101 #
b10001011 (
b110001011 &
#50000
b10000001 !
b11110010 $
b10001111 #
b1011100 (
b101011100 &
#55000
b10101101 !
b11000101 $
b11101000 #
b10000001 (
b110000001 &
#60000
0"
b11101011 !
1%
b101101 $
b10111101 #
b10101101 (
b110101101 &
#65000
b1101101 !
0%
b1010 $
b1100011 #
0'
b11101011 (
b11101011 &
#70000
b11001011 !
1%
b10101010 $
b100000 #
b1101101 (
b1101101 &
#75000
b10101010 !
b10011 $
b10010110 #
b11001011 (
b11001011 &
#80000
b10111111 !
b1101011 $
b1010011 #
b10101010 (
b10101010 &
#85000
0"
b10110001 !
b10101110 $
b10 #
b10111111 (
b10111111 &
#90000
b11110010 !
0%
b100011 $
b11001111 #
b10110001 (
b10110001 &
#95000
1"
b110 !
b111100 $
b11001010 #
b11110010 (
b11110010 &
#100000
0"
b11001011 !
b1000001 $
b10001010 #
1'
b110 (
b100000110 &
#105000
1"
b10 !
1%
b10001001 $
b1111000 #
0'
b11001011 (
b11001011 &
#110000
b1111100 !
0%
b11000110 $
b10110110 #
1'
b10 (
b100000010 &
#115000
b1111100 (
b101111100 &
